pythonbeid/__init__.py
pythonbeid/card_reader.py
tests/__init__.py
tests/test_card_reader.py
pythonbeid-0.1.1.dist-info/LICENSE
pythonbeid-0.1.1.dist-info/METADATA
pythonbeid-0.1.1.dist-info/WHEEL
pythonbeid-0.1.1.dist-info/top_level.txt
pythonbeid-0.1.1.dist-info/RECORD
