Metadata-Version: 2.1
Name: pythonbeid
Version: 0.1.1
Summary: Un module pour lire les informations des cartes d'identité belges
Home-page: https://github.com/Lapin-Blanc/pythonbeid
Author: Fabien Toune
Author-email: fabien.toune@gmail.com
Classifier: Programming Language :: Python :: 3
Classifier: License :: OSI Approved :: MIT License
Classifier: Operating System :: OS Independent
Requires-Python: >=3.6
License-File: LICENSE
Requires-Dist: pyscard
